AUTHORS
ChangeLog
LICENSE.md
README.rst
requirements.txt
setup.cfg
setup.py
haproxytool/__init__.py
haproxytool/acl.py
haproxytool/backend.py
haproxytool/cli.py
haproxytool/dump.py
haproxytool/frontend.py
haproxytool/haproxy.py
haproxytool/map.py
haproxytool/server.py
haproxytool/utils.py
haproxytool.egg-info/PKG-INFO
haproxytool.egg-info/SOURCES.txt
haproxytool.egg-info/dependency_links.txt
haproxytool.egg-info/entry_points.txt
haproxytool.egg-info/not-zip-safe
haproxytool.egg-info/pbr.json
haproxytool.egg-info/requires.txt
haproxytool.egg-info/top_level.txt