Metadata-Version: 1.2
Name: haproxytool
Version: 0.5.6
Summary: A tool to manage HAProxy via stats socket
Home-page: https://github.com/unixsurfer/haproxytool
Author: Pavlos Parissis
Author-email: pavlos.parissis@gmail.com
Maintainer: Pavlos Parissis
Maintainer-email: pavlos.parissis@gmail.com
License: Apache 2.0
Keywords: haproxy,haproxyadmin,haproxytool,tool
Platform: UNKNOWN
Classifier: Development Status :: 5 - Production/Stable
Classifier: Environment :: Console
Classifier: Intended Audience :: Information Technology
Classifier: Intended Audience :: System Administrators
Classifier: Natural Language :: English
Classifier: Operating System :: POSIX
Classifier: Programming Language :: Python :: 2.7
Classifier: Programming Language :: Python :: 3.4
Classifier: Programming Language :: Python :: 3.5
Classifier: Topic :: Utilities
